odoo/addons/project_task_stage_lock/README.rst
odoo/addons/project_task_stage_lock/__init__.py
odoo/addons/project_task_stage_lock/__manifest__.py
odoo/addons/project_task_stage_lock/i18n/it.po
odoo/addons/project_task_stage_lock/i18n/project_task_stage_lock.pot
odoo/addons/project_task_stage_lock/readme/CONTRIBUTORS.md
odoo/addons/project_task_stage_lock/readme/DESCRIPTION.md
odoo/addons/project_task_stage_lock/static/description/icon.png
odoo/addons/project_task_stage_lock/static/description/index.html
odoo/addons/project_task_stage_lock/static/src/views/project_task_kanban_renderer.esm.js
odoo/addons/project_task_stage_lock/views/project.xml
odoo_addon_project_task_stage_lock-18.0.1.0.0.3.dist-info/METADATA
odoo_addon_project_task_stage_lock-18.0.1.0.0.3.dist-info/WHEEL
odoo_addon_project_task_stage_lock-18.0.1.0.0.3.dist-info/top_level.txt
odoo_addon_project_task_stage_lock-18.0.1.0.0.3.dist-info/RECORD
