Metadata-Version: 2.1
Name: odoo-addon-project_task_stage_lock
Version: 18.0.1.0.0.3
Requires-Python: >=3.10
Requires-Dist: odoo==18.0.*
Summary: Locks the Stages in the Kanban view of the project task to avoid modification of the stages in other projects. Also removes the default group by in the stages list view to be able to see the stages order.
Home-page: https://github.com/OCA/project
License: AGPL-3
Author: ForgeFlow, Odoo Community Association (OCA)
Author-email: support@odoo-community.org
Classifier: Programming Language :: Python
Classifier: Framework :: Odoo
Classifier: Framework :: Odoo :: 18.0
Classifier: License :: OSI Approved :: GNU Affero General Public License v3
